<annotation>
	<folder>pens</folder>
	<filename>istockphoto-185078634-612x612.jpg</filename>
	<path>D:\pens\istockphoto-185078634-612x612.jpg</path>
	<source>
		<database>Unknown</database>
	</source>
	<size>
		<width>612</width>
		<height>408</height>
		<depth>3</depth>
	</size>
	<segmented>0</segmented>
	<object>
		<name>pen</name>
		<pose>Unspecified</pose>
		<truncated>0</truncated>
		<difficult>0</difficult>
		<bndbox>
			<xmin>51</xmin>
			<ymin>49</ymin>
			<xmax>534</xmax>
			<ymax>321</ymax>
		</bndbox>
	</object>
</annotation>
