<annotation>
	<folder>pens</folder>
	<filename>istockphoto-457488605-612x612.jpg</filename>
	<path>D:\pens\istockphoto-457488605-612x612.jpg</path>
	<source>
		<database>Unknown</database>
	</source>
	<size>
		<width>612</width>
		<height>393</height>
		<depth>3</depth>
	</size>
	<segmented>0</segmented>
	<object>
		<name>pen</name>
		<pose>Unspecified</pose>
		<truncated>0</truncated>
		<difficult>0</difficult>
		<bndbox>
			<xmin>37</xmin>
			<ymin>75</ymin>
			<xmax>576</xmax>
			<ymax>326</ymax>
		</bndbox>
	</object>
</annotation>
